flask_remote_file.py
flask_remote_file-0.1.0.dist-info/DESCRIPTION.rst
flask_remote_file-0.1.0.dist-info/METADATA
flask_remote_file-0.1.0.dist-info/RECORD
flask_remote_file-0.1.0.dist-info/WHEEL
flask_remote_file-0.1.0.dist-info/metadata.json
flask_remote_file-0.1.0.dist-info/top_level.txt
