Metadata-Version: 2.0
Name: flask-remote-file
Version: 0.1.0
Summary: Flask extension to serve remote files via sftp
Home-page: https://github.com/frostming/flask-remote-file
Author: Frost Ming
Author-email: mianghong@gmail.com
License: MIT
Platform: UNKNOWN
Classifier: Development Status :: 3 - Alpha
Classifier: Environment :: Web Environment
Classifier: Intended Audience :: Developers
Classifier: License :: OSI Approved :: MIT License
Classifier: Operating System :: OS Independent
Classifier: Programming Language :: Python
Requires-Dist: paramiko
Requires-Dist: flask
